periodicgw/__init__.py
periodicgw/periodicgw_utils.py
periodicgw-1.1.dist-info/LICENSE.txt
periodicgw-1.1.dist-info/METADATA
periodicgw-1.1.dist-info/WHEEL
periodicgw-1.1.dist-info/top_level.txt
periodicgw-1.1.dist-info/RECORD
