Metadata-Version: 2.1
Name: periodicgw
Version: 1.1
Summary: Generates doubly-periodic random 2D Darcy flow fields with arbitrary mean flow direction
Home-page: https://gitlab.com/scottkalevhansen/periodic-gw
Author: Scott K. Hansen, Lian Zhou
Author-email: skh@bgu.ac.il
License: UNKNOWN
Platform: UNKNOWN
Requires-Dist: numpy
Requires-Dist: matplotlib
Requires-Dist: scipy
